pyZPL/__init__.py
pyZPL/zpl.py
pyZPL/zpleditor.py
pyZPL/zpl/__init__.py
pyZPL/zpl/defaults.py
pyZPL/zpl/zpl.py
pyZPL/zpl/shape/__init__.py
pyZPL/zpl/shape/box.py
pyZPL/zpl/shape/horizontal_line.py
pyZPL/zpl/shape/vertical_line.py
pyZPL/zpl/text/__init__.py
pyZPL/zpl/text/native_text.py
pyZPL/zpl/text/text.py
pyZPL/zpl/text/text_line.py
pyZPLEditor-0.1.dist-info/LICENSE
pyZPLEditor-0.1.dist-info/METADATA
pyZPLEditor-0.1.dist-info/WHEEL
pyZPLEditor-0.1.dist-info/top_level.txt
pyZPLEditor-0.1.dist-info/RECORD
