Metadata-Version: 2.1
Name: pyZPLEditor
Version: 0.1
Summary: A ZPL editor
Home-page: https://github.com/divad1196/pyZPL
Author: Gallay David
Author-email: davidtennis96@hotmail.com
License: UNKNOWN
Platform: UNKNOWN
Classifier: Programming Language :: Python :: 3
Classifier: License :: OSI Approved :: GNU Affero General Public License v3
Classifier: Operating System :: OS Independent
Requires-Dist: kivy
